README.rst
setup.py
copius_api/__init__.py
copius_api/api.py
copius_api.egg-info/PKG-INFO
copius_api.egg-info/SOURCES.txt
copius_api.egg-info/dependency_links.txt
copius_api.egg-info/requires.txt
copius_api.egg-info/top_level.txt
tests/__init__.py
tests/test_api.py