Metadata-Version: 2.1
Name: copius-api
Version: 1.4.1
Summary: Transcription & orthography toolset
Home-page: https://github.com/martino-vic/copius_api
Author: Viktor Martinović
Author-email: viktoringermany@gmail.com
License: MIT
Download-URL: https://github.com/martino-vic/copius_api/archive/refs/tags/v1.4.1.tar.gz
Project-URL: continuous integration, https://app.circleci.com/pipelines/github/martino-vic/copius_api?branch=master
Keywords: linguistics,transcription
Platform: Linux
Classifier: Development Status :: 3 - Alpha
Classifier: Intended Audience :: Science/Research
Classifier: Topic :: Scientific/Engineering
Classifier: Topic :: Text Processing :: Linguistic
Classifier: License :: OSI Approved :: MIT License
Classifier: Natural Language :: English
Classifier: Operating System :: POSIX :: Linux
Classifier: Programming Language :: Python :: 3.7
Classifier: Programming Language :: Python :: 3.8
Classifier: Programming Language :: Python :: 3.9
Classifier: Programming Language :: Python :: 3.10
Classifier: Programming Language :: Python :: 3.11
Requires-Python: >=3.7
Provides-Extra: dev
Provides-Extra: test
